mcli/__init__.py
mcli/cli.py
mcli-0.3.2.dist-info/DESCRIPTION.rst
mcli-0.3.2.dist-info/METADATA
mcli-0.3.2.dist-info/RECORD
mcli-0.3.2.dist-info/WHEEL
mcli-0.3.2.dist-info/entry_points.txt
mcli-0.3.2.dist-info/metadata.json
mcli-0.3.2.dist-info/top_level.txt
