Metadata-Version: 2.0
Name: mcli
Version: 0.3.2
Summary: MarketMaker CLI
Home-page: https://github.com/Monaize/mcli
Author: Maxime Saddok
Author-email: maxime@monaize.com
License: MIT license
Keywords: mcli
Platform: UNKNOWN
Classifier: Development Status :: 2 - Pre-Alpha
Classifier: Intended Audience :: Developers
Classifier: License :: OSI Approved :: MIT License
Classifier: Natural Language :: English
Classifier: Programming Language :: Python :: 2
Classifier: Programming Language :: Python :: 2.6
Classifier: Programming Language :: Python :: 2.7
Classifier: Programming Language :: Python :: 3
Classifier: Programming Language :: Python :: 3.3
Classifier: Programming Language :: Python :: 3.4
Classifier: Programming Language :: Python :: 3.5
Requires-Dist: Click (>=6.0)
Requires-Dist: requests (==2.18.4)
